capp/__init__.py
capp/cli/chaoscapy.py
capp/client.py
capp/conn_factory.py
capp/consts.py
capp/instructions.py
capp/pb/instructions_pb2.py
capp/pb/instructions_pb2.pyi
capp/retry.py
capp/types.py
capp/wireformat.py
capp_py-0.0.2.dist-info/METADATA
capp_py-0.0.2.dist-info/WHEEL
capp_py-0.0.2.dist-info/entry_points.txt
capp_py-0.0.2.dist-info/RECORD
