Metadata-Version: 2.1
Name: capp-py
Version: 0.0.2
Summary: Python clienet for capp
Author-Email: Capp Team <gocappio@gmail.com>
License: Apache 2.0
Requires-Python: <4.0,>=3.9
Requires-Dist: protobuf<6.0.0,>=5.27.1
